pyapi_compat_if/__init__.py
pyapi_compat_if/pkginfo.py
pyapi_compat_if/__build_num__.py
pyapi_compat_if/core.cpython-39-x86_64-linux-gnu.so
pyapi_compat_if-0.0.1.8428028712.dist-info/RECORD
pyapi_compat_if-0.0.1.8428028712.dist-info/entry_points.txt
pyapi_compat_if-0.0.1.8428028712.dist-info/METADATA
pyapi_compat_if-0.0.1.8428028712.dist-info/WHEEL
pyapi_compat_if-0.0.1.8428028712.dist-info/top_level.txt
pyapi_compat_if-0.0.1.8428028712.dist-info/LICENSE
