Metadata-Version: 2.1
Name: pyapi-compat-if
Version: 0.0.1.8428028712
Summary: Core Verification Stimulus and Coverage library
Home-page: https://github.com/mballance-utils/pyapi-compat-if
Author: Matthew Ballance
Author-email: matt.ballance@gmail.com
License: Apache 2.0
Keywords: SystemVerilog,Verilog,RTL,Python
License-File: LICENSE
Requires-Dist: debug-mgr
